odoo/addons/edi_voxel_sale_secondary_unit_oca/README.rst
odoo/addons/edi_voxel_sale_secondary_unit_oca/__init__.py
odoo/addons/edi_voxel_sale_secondary_unit_oca/__manifest__.py
odoo/addons/edi_voxel_sale_secondary_unit_oca/i18n/edi_voxel_sale_secondary_unit.pot
odoo/addons/edi_voxel_sale_secondary_unit_oca/i18n/edi_voxel_sale_secondary_unit_oca.pot
odoo/addons/edi_voxel_sale_secondary_unit_oca/models/__init__.py
odoo/addons/edi_voxel_sale_secondary_unit_oca/models/sale_order.py
odoo/addons/edi_voxel_sale_secondary_unit_oca/readme/CONTRIBUTORS.rst
odoo/addons/edi_voxel_sale_secondary_unit_oca/readme/DESCRIPTION.rst
odoo/addons/edi_voxel_sale_secondary_unit_oca/readme/USAGE.rst
odoo/addons/edi_voxel_sale_secondary_unit_oca/static/description/icon.png
odoo/addons/edi_voxel_sale_secondary_unit_oca/static/description/index.html
odoo/addons/edi_voxel_sale_secondary_unit_oca/tests/__init__.py
odoo/addons/edi_voxel_sale_secondary_unit_oca/tests/test_edi_voxel_sale_secondary_unit.py
odoo_addon_edi_voxel_sale_secondary_unit_oca-15.0.1.0.0.1.dist-info/METADATA
odoo_addon_edi_voxel_sale_secondary_unit_oca-15.0.1.0.0.1.dist-info/WHEEL
odoo_addon_edi_voxel_sale_secondary_unit_oca-15.0.1.0.0.1.dist-info/top_level.txt
odoo_addon_edi_voxel_sale_secondary_unit_oca-15.0.1.0.0.1.dist-info/RECORD
