Metadata-Version: 2.1
Name: odoo-addon-edi-voxel-sale-secondary-unit-oca
Version: 15.0.1.0.0.1
Summary: Map Voxel UoM to Sale Secondary UoM and Use Them
Home-page: https://github.com/OCA/edi
Author: Tecnativa, Odoo Community Association (OCA)
Author-email: support@odoo-community.org
License: AGPL-3
Platform: UNKNOWN
Classifier: Programming Language :: Python
Classifier: Framework :: Odoo
Classifier: Framework :: Odoo :: 15.0
Classifier: License :: OSI Approved :: GNU Affero General Public License v3
Requires-Python: >=3.8
Requires-Dist: odoo-addon-edi-voxel-sale-order-import-oca <15.1dev,>=15.0dev
Requires-Dist: odoo-addon-edi-voxel-secondary-unit-oca <15.1dev,>=15.0dev
Requires-Dist: odoo-addon-sale-order-secondary-unit <15.1dev,>=15.0dev
Requires-Dist: odoo <15.1dev,>=15.0a
